atspm/__init__.py
atspm/data_aggregator.py
atspm/data_loader.py
atspm/data_saver.py
atspm/sample_data.py
atspm/signal_data_processor.py
atspm/utils.py
atspm/data/sample_config.parquet
atspm/data/sample_raw_data.parquet
atspm/queries/actuations.sql
atspm/queries/arrival_on_green.sql
atspm/queries/communications.sql
atspm/queries/coordination.sql
atspm/queries/coordination_agg.sql
atspm/queries/full_ped.sql
atspm/queries/has_data.sql
atspm/queries/ped.sql
atspm/queries/ped_delay.sql
atspm/queries/phase_wait.sql
atspm/queries/split_failures.sql
atspm/queries/splits.sql
atspm/queries/terminations.sql
atspm/queries/timeline.sql
atspm/queries/unique_ped.sql
atspm/queries/yellow_red.sql
atspm-2.1.1.dist-info/licenses/LICENSE
atspm-2.1.1.dist-info/METADATA
atspm-2.1.1.dist-info/WHEEL
atspm-2.1.1.dist-info/top_level.txt
atspm-2.1.1.dist-info/RECORD
