Metadata-Version: 2.4
Name: atspm
Version: 2.1.1
Summary: Aggregates hi-res data from ATC traffic signal controllers into 15-minute binned ATSPM/performance measures.
Author-email: Shawn Strasser <shawn.strasser@odot.oregon.gov>
Classifier: Programming Language :: Python :: 3
Classifier: License :: OSI Approved :: MIT License
Classifier: Operating System :: OS Independent
Requires-Python: >=3.10
License-File: LICENSE
Requires-Dist: traffic-anomaly>=2.4.0
Requires-Dist: jinja2
Requires-Dist: pyarrow
Requires-Dist: pyarrow_hotfix
Dynamic: license-file
